arvi1/__init__.py
arvi1/arviprogram1.py
arvi2/__init__.py
arvi2/arviprogram2.py
arvi2/arviprogram22.py
ArviPackage-0.0.3.dist-info/METADATA
ArviPackage-0.0.3.dist-info/WHEEL
ArviPackage-0.0.3.dist-info/top_level.txt
ArviPackage-0.0.3.dist-info/RECORD
