Metadata-Version: 2.1
Name: ArviPackage
Version: 0.0.3
Summary: My first Python package
Author: Aravind
Author-email: aravindmoguram8@gmail.com
Keywords: python,first package,Basic Mathamatic Operations
Classifier: Development Status :: 3 - Alpha
Classifier: Intended Audience :: Education
Classifier: Programming Language :: Python :: 2
Classifier: Programming Language :: Python :: 3
Classifier: Operating System :: MacOS :: MacOS X
Classifier: Operating System :: Microsoft :: Windows
